LICENSE
MANIFEST.in
README.rst
buildout.cfg
develop.cfg
requirements.txt
setup.py
version.txt
bob/__init__.py
bob.learn.boosting.egg-info/PKG-INFO
bob.learn.boosting.egg-info/SOURCES.txt
bob.learn.boosting.egg-info/dependency_links.txt
bob.learn.boosting.egg-info/entry_points.txt
bob.learn.boosting.egg-info/not-zip-safe
bob.learn.boosting.egg-info/requires.txt
bob.learn.boosting.egg-info/top_level.txt
bob/learn/__init__.py
bob/learn/boosting/Boosting.py
bob/learn/boosting/ExponentialLoss.py
bob/learn/boosting/LUTTrainer.py
bob/learn/boosting/LogitLoss.py
bob/learn/boosting/LossFunction.py
bob/learn/boosting/StumpTrainer.py
bob/learn/boosting/TangentialLoss.py
bob/learn/boosting/__init__.py
bob/learn/boosting/boosted_machine.cpp
bob/learn/boosting/jesorsky_loss.cpp
bob/learn/boosting/loss_function.cpp
bob/learn/boosting/lut_machine.cpp
bob/learn/boosting/lut_trainer.cpp
bob/learn/boosting/main.cpp
bob/learn/boosting/main.h
bob/learn/boosting/stump_machine.cpp
bob/learn/boosting/utils.py
bob/learn/boosting/version.cpp
bob/learn/boosting/weak_machine.cpp
bob/learn/boosting/cpp/BoostedMachine.cpp
bob/learn/boosting/cpp/JesorskyLoss.cpp
bob/learn/boosting/cpp/LUTMachine.cpp
bob/learn/boosting/cpp/LUTTrainer.cpp
bob/learn/boosting/cpp/LossFunction.cpp
bob/learn/boosting/cpp/StumpMachine.cpp
bob/learn/boosting/data/mnist.tar.bz2
bob/learn/boosting/data/testdata.hdf5
bob/learn/boosting/examples/__init__.py
bob/learn/boosting/examples/mnist.py
bob/learn/boosting/include/bob.learn.boosting/BoostedMachine.h
bob/learn/boosting/include/bob.learn.boosting/Functions.h
bob/learn/boosting/include/bob.learn.boosting/JesorskyLoss.h
bob/learn/boosting/include/bob.learn.boosting/LUTMachine.h
bob/learn/boosting/include/bob.learn.boosting/LUTTrainer.h
bob/learn/boosting/include/bob.learn.boosting/LossFunction.h
bob/learn/boosting/include/bob.learn.boosting/StumpMachine.h
bob/learn/boosting/include/bob.learn.boosting/WeakMachine.h
bob/learn/boosting/include/bob.learn.boosting/config.h
bob/learn/boosting/tests/__init__.py
bob/learn/boosting/tests/test_boosting.py
bob/learn/boosting/tests/test_example.py
bob/learn/boosting/tests/test_loss_exp.py
bob/learn/boosting/tests/test_loss_jes.py
bob/learn/boosting/tests/test_loss_log.py
bob/learn/boosting/tests/test_machines.py
