Metadata-Version: 1.1
Name: bob.learn.boosting
Version: 2.0.14
Summary: Boosting framework for Bob
Home-page: https://gitlab.idiap.ch/bob/bob.learn.boosting
Author: Manuel Guenther (with help of Rakesh Mehta)
Author-email: manuel.guenther@idiap.ch
License: BSD
Platform: UNKNOWN
Classifier: Framework :: Bob
Classifier: Development Status :: 4 - Beta
Classifier: Intended Audience :: Developers
Classifier: License :: OSI Approved :: BSD License
Classifier: Natural Language :: English
Classifier: Programming Language :: Python
Classifier: Topic :: Scientific/Engineering :: Artificial Intelligence
